CHANGES.txt
MANIFEST.in
README.txt
__init__.py
fabfile.py
setup.py
Art3dUtils.egg-info/PKG-INFO
Art3dUtils.egg-info/SOURCES.txt
Art3dUtils.egg-info/dependency_links.txt
Art3dUtils.egg-info/requires.txt
Art3dUtils.egg-info/top_level.txt
art3dutils/__init__.py
art3dutils/models.py
art3dutils/svg.mako
art3dutils/utilities.py
art3dutils/tests/__init__.py
art3dutils/tests/tests.py
art3dutils/tests/tests.pyc
art3dutils/tests/svg/paths.svg~
art3dutils/tests/svg/polygon_rect_path.svg
art3dutils/tests/svg/svg.mako
art3dutils/tests/xml/1s.xml