Metadata-Version: 1.0
Name: Art3dUtils
Version: 0.3.6.8
Summary: Object models for storing and utilities for processing architecture data
Home-page: UNKNOWN
Author: Max Korinets
Author-email: mkorinets@gmail.com
License: MIT
Platform: UNKNOWN
